unit_sphere_a_designs/__init__.py
unit_sphere_a_designs/local.py
unit_sphere_a_designs/tools.py
unit_sphere_a_designs-0.1.0.dist-info/METADATA
unit_sphere_a_designs-0.1.0.dist-info/WHEEL
unit_sphere_a_designs-0.1.0.dist-info/top_level.txt
unit_sphere_a_designs-0.1.0.dist-info/RECORD
