Metadata-Version: 2.1
Name: unit-sphere-a-designs
Version: 0.1.0
Summary: A package for local search algorithms on unit sphere designs
Home-page: https://github.com/adityapillai/unit_sphere_a_designs
Author: Aditya Pillai
Author-email: aditya.pilai63916@gmail.com
License: UNKNOWN
Platform: UNKNOWN
Classifier: Programming Language :: Python :: 3
Classifier: License :: OSI Approved :: MIT License
Classifier: Operating System :: OS Independent
Requires-Python: >=3.6
Requires-Dist: numpy
Requires-Dist: pytest
